financas/__init__.py
financas/carteira.py
financas/main.py
financas/transacao.py
financas-0.0.1.dist-info/METADATA
financas-0.0.1.dist-info/WHEEL
financas-0.0.1.dist-info/top_level.txt
financas-0.0.1.dist-info/RECORD
