Metadata-Version: 2.4
Name: financas
Version: 0.0.1
Summary: Pequeno estudo de um programa de finanças pessoais
Home-page: https://github.com/boechat/package-template/
Author: boechat
Author-email: boechat.andre@gmail.com
Requires-Python: >=3.8
Dynamic: author
Dynamic: author-email
Dynamic: description
Dynamic: description-content-type
Dynamic: home-page
Dynamic: requires-python
Dynamic: summary
